setup.py
lls_rpa_hello/__init__.py
lls_rpa_hello/hello.py
lls_rpa_hello.egg-info/PKG-INFO
lls_rpa_hello.egg-info/SOURCES.txt
lls_rpa_hello.egg-info/dependency_links.txt
lls_rpa_hello.egg-info/entry_points.txt
lls_rpa_hello.egg-info/requires.txt
lls_rpa_hello.egg-info/top_level.txt