Metadata-Version: 1.2
Name: lls-rpa-hello
Version: 1.0.1
Summary: lls_rpa_hello
Home-page: https://pypi.org/user/xianddd/
Author: xianddd
Author-email: xianddd@126.com
License: MIT License
Platform: UNKNOWN
Requires-Python: >=3.6
